openai_simple_chat/__init__.py
openai_simple_chat/base.py
openai_simple_chat/chat_with_ollama.py
openai_simple_chat/chat_with_openai.py
openai_simple_chat/jsonutils.py
openai_simple_chat/settings.py
openai_simple_chat/template.py
openai_simple_chat_django_template_example/__init__.py
openai_simple_chat_django_template_example/admin.py
openai_simple_chat_django_template_example/apps.py
openai_simple_chat_django_template_example/models.py
openai_simple_chat_django_template_example/tests.py
openai_simple_chat_django_template_example/views.py
openai_simple_chat_django_template_example/migrations/__init__.py
openai_simple_chat_django_template_test/__init__.py
openai_simple_chat_django_template_test/asgi.py
openai_simple_chat_django_template_test/settings.py
openai_simple_chat_django_template_test/urls.py
openai_simple_chat_django_template_test/wsgi.py
openai_simple_chat-0.1.8.dist-info/LICENSE
openai_simple_chat-0.1.8.dist-info/METADATA
openai_simple_chat-0.1.8.dist-info/WHEEL
openai_simple_chat-0.1.8.dist-info/top_level.txt
openai_simple_chat-0.1.8.dist-info/RECORD
