Metadata-Version: 2.1
Name: openai-simple-chat
Version: 0.1.8
Summary: 大模型对话标准接口。支持模板对话、JSON对话等。
Author: rRR0VrFP
Maintainer: rRR0VrFP
License: Apache License, Version 2.0
Keywords: openai-simple-chat
Classifier: Development Status :: 5 - Production/Stable
Classifier: Intended Audience :: Developers
Classifier: Topic :: Software Development :: Libraries :: Python Modules
Classifier: License :: OSI Approved :: Apache Software License
Classifier: Programming Language :: Python :: 3
Classifier: Programming Language :: Python :: 3 :: Only
License-File: LICENSE
Requires-Dist: zenutils
Requires-Dist: python-environment-settings
Requires-Dist: jinja2
Requires-Dist: django
Requires-Dist: openai
Requires-Dist: ollama
